jrpytensorflow/__init__.py
jrpytensorflow/__version__.py
jrpytensorflow/datasets/__init__.py
jrpytensorflow/datasets/data/walking.zip
jrpytensorflow/vignettes.py
jrpytensorflow-0.1.15.dist-info/METADATA
jrpytensorflow-0.1.15.dist-info/WHEEL
jrpytensorflow-0.1.15.dist-info/RECORD
